Metadata-Version: 1.0
Name: bigaussian-distributions
Version: 1.0
Summary: A package for calculating Gaussian or Binomial distributions on a described data
Home-page: UNKNOWN
Author: UNKNOWN
Author-email: UNKNOWN
License: UNKNOWN
Platform: UNKNOWN
